Metadata-Version: 1.1
Name: fast2webp
Version: 1.1.10
Summary: A Python script that converts image files in PNG, JPG, JPEG, BMP, GIF batch (recursively) to webp format
Home-page: https://github.com/Mogeko/fast2webp
Author: Mogeko
Author-email: zhengjunyi@live.com
License: MIT
Project-URL: GitHub, https://github.com/Mogeko/fast2webp
Keywords: webp
Platform: Linux
Classifier: Development Status :: 3 - Alpha
Classifier: Operating System :: POSIX :: Linux
Classifier: Intended Audience :: Developers
Classifier: Topic :: Software Development
Classifier: Natural Language :: Chinese (Simplified)
Classifier: License :: OSI Approved :: MIT License
Classifier: Programming Language :: Python :: 3 :: Only
Classifier: Programming Language :: Python :: 3.5
Classifier: Programming Language :: Python :: 3.6
Classifier: Programming Language :: Python :: 3.7
